globber/__init__.py
globber/globber.py
globber-0.2.1.dist-info/LICENSE
globber-0.2.1.dist-info/METADATA
globber-0.2.1.dist-info/WHEEL
globber-0.2.1.dist-info/top_level.txt
globber-0.2.1.dist-info/RECORD
