Metadata-Version: 2.1
Name: globber
Version: 0.2.1
Summary: Library for string matching with glob patterns
Home-page: https://github.com/asharov/globber
Author: Jaakko Kangasharju
Author-email: ashar@iki.fi
License: UNKNOWN
Platform: UNKNOWN
Classifier: Programming Language :: Python :: 3
Classifier: License :: OSI Approved :: Apache Software License
Classifier: Development Status :: 3 - Alpha
Classifier: Operating System :: OS Independent
